odoo/addons/sale_probability_amount/README.rst
odoo/addons/sale_probability_amount/__init__.py
odoo/addons/sale_probability_amount/__manifest__.py
odoo/addons/sale_probability_amount/data/ir_config_parameter.xml
odoo/addons/sale_probability_amount/i18n/fr.po
odoo/addons/sale_probability_amount/i18n/sale_probability_amount.pot
odoo/addons/sale_probability_amount/models/__init__.py
odoo/addons/sale_probability_amount/models/sale_order.py
odoo/addons/sale_probability_amount/readme/CONTRIBUTORS.rst
odoo/addons/sale_probability_amount/readme/DESCRIPTION.rst
odoo/addons/sale_probability_amount/static/description/icon.png
odoo/addons/sale_probability_amount/static/description/index.html
odoo/addons/sale_probability_amount/tests/__init__.py
odoo/addons/sale_probability_amount/tests/test_sale_probability_amount.py
odoo/addons/sale_probability_amount/views/sale_views.xml
odoo14_addon_sale_probability_amount-14.0.1.0.1.dist-info/METADATA
odoo14_addon_sale_probability_amount-14.0.1.0.1.dist-info/WHEEL
odoo14_addon_sale_probability_amount-14.0.1.0.1.dist-info/top_level.txt
odoo14_addon_sale_probability_amount-14.0.1.0.1.dist-info/RECORD
